openai_dbd/__init__.py
openai_dbd/openai_dbd.py
openai_dbd-0.0.30.dist-info/METADATA
openai_dbd-0.0.30.dist-info/WHEEL
openai_dbd-0.0.30.dist-info/top_level.txt
openai_dbd-0.0.30.dist-info/RECORD
